b_cfn_twilio_task_queue/__init__.py
b_cfn_twilio_task_queue/function.py
b_cfn_twilio_task_queue/resource.py
b_cfn_twilio_task_queue/source/__init__.py
b_cfn_twilio_task_queue/source/action.py
b_cfn_twilio_task_queue/source/cfnresponse.py
b_cfn_twilio_task_queue/source/index.py
b_cfn_twilio_task_queue-0.0.2.dist-info/LICENSE
b_cfn_twilio_task_queue-0.0.2.dist-info/METADATA
b_cfn_twilio_task_queue-0.0.2.dist-info/WHEEL
b_cfn_twilio_task_queue-0.0.2.dist-info/top_level.txt
b_cfn_twilio_task_queue-0.0.2.dist-info/RECORD
